urwid_satext/__init__.py
urwid_satext/files_management.py
urwid_satext/keys.py
urwid_satext/sat_widgets.py
urwid_satext-0.8.0.data/data/share/doc/urwid_satext/CHANGELOG
urwid_satext-0.8.0.data/data/share/doc/urwid_satext/COPYING
urwid_satext-0.8.0.data/data/share/doc/urwid_satext/COPYING.LESSER
urwid_satext-0.8.0.data/data/share/doc/urwid_satext/README
urwid_satext-0.8.0.data/data/share/doc/urwid_satext/examples/file_dialog.py
urwid_satext-0.8.0.data/data/share/doc/urwid_satext/examples/menu.py
urwid_satext-0.8.0.data/data/share/locale/fr/LC_MESSAGES/urwid_satext.mo
urwid_satext-0.8.0.dist-info/COPYING
urwid_satext-0.8.0.dist-info/COPYING.LESSER
urwid_satext-0.8.0.dist-info/METADATA
urwid_satext-0.8.0.dist-info/WHEEL
urwid_satext-0.8.0.dist-info/top_level.txt
urwid_satext-0.8.0.dist-info/RECORD
