Metadata-Version: 2.1
Name: urwid-satext
Version: 0.8.0
Summary: SàT extension widgets for Urwid
Home-page: https://wiki.goffi.org/w/index.php/Urwid-satext
Author: Goffi (Jérôme Poisson)
Author-email: goffi@goffi.org
License: UNKNOWN
Platform: UNKNOWN
Classifier: Programming Language :: Python :: 3 :: Only
Classifier: Programming Language :: Python :: 3.7
Classifier: Programming Language :: Python :: 3.8
Classifier: Programming Language :: Python :: 3.9
Classifier: Environment :: Console
Classifier: License :: OSI Approved :: GNU Library or Lesser General Public License (LGPL)
Classifier: Intended Audience :: Developers
License-File: COPYING
License-File: COPYING.LESSER
Requires-Dist: urwid (>=1.2.0)
